MANIFEST.in
setup.cfg
setup.py
tw/__init__.py
tw.starrating.egg-info/PKG-INFO
tw.starrating.egg-info/SOURCES.txt
tw.starrating.egg-info/dependency_links.txt
tw.starrating.egg-info/entry_points.txt
tw.starrating.egg-info/namespace_packages.txt
tw.starrating.egg-info/not-zip-safe
tw.starrating.egg-info/paster_plugins.txt
tw.starrating.egg-info/requires.txt
tw.starrating.egg-info/top_level.txt
tw/starrating/__init__.py
tw/starrating/release.py
tw/starrating/samples.py
tw/starrating/widgets.py
tw/starrating/static/delete.gif
tw/starrating/static/jquery.MetaData.js
tw/starrating/static/jquery.rating.css
tw/starrating/static/jquery.rating.js
tw/starrating/static/jquery.rating.pack.js
tw/starrating/static/star.gif