Metadata-Version: 1.0
Name: tw.starrating
Version: 1.0.2
Summary: jQuery Star Rating Plugin for ToscaWidgets
Home-page: http://code.google.com/p/pyxis-webframework/
Author: Pyxis Developer Team
Author-email: pyxis-dev@ml.triax.jp
License: UNKNOWN
Keywords: toscawidgets.widgets
Platform: UNKNOWN
Classifier: Development Status :: 3 - Alpha
Classifier: Environment :: Web Environment
Classifier: Environment :: Web Environment :: ToscaWidgets
Classifier: Topic :: Software Development :: Libraries :: Python Modules
Classifier: Topic :: Software Development :: Widget Sets
Classifier: Intended Audience :: Developers
Classifier: Operating System :: OS Independent
Classifier: Programming Language :: Python
